<?xml version="1.0" encoding="UTF-8"?>
<objects serializationModel="Studio.02.00.00">
	<object class="EncodingSetting" id="{4663e480-96f7-49e6-ad18-1bf8dc289be2}">
		<property name="encodingFormat">
			<value>3</value>
		</property>
		<property name="quality">
			<value>37</value>
		</property>
		<relationship name="platform">
			<destination>{2a02cb05-0b58-4446-8123-9f30e2c2c9b8}</destination>
		</relationship>
		<relationship name="encodable">
			<destination>{2a02cb05-0b58-4446-8123-9f30e2c2c9b8}</destination>
		</relationship>
	</object>
</objects>
